zope/app/pagetemplate/__init__.py
zope/app/pagetemplate/configure.zcml
zope/app/pagetemplate/engine.py
zope/app/pagetemplate/i18n.py
zope/app/pagetemplate/interfaces.py
zope/app/pagetemplate/meta.zcml
zope/app/pagetemplate/metaconfigure.py
zope/app/pagetemplate/namedtemplate.py
zope/app/pagetemplate/simpleviewclass.py
zope/app/pagetemplate/talesapi.py
zope/app/pagetemplate/urlquote.py
zope/app/pagetemplate/viewpagetemplatefile.py
zope/app/pagetemplate/tests/__init__.py
zope/app/pagetemplate/tests/inner.pt
zope/app/pagetemplate/tests/intermediate.pt
zope/app/pagetemplate/tests/outer.pt
zope/app/pagetemplate/tests/test_binding.py
zope/app/pagetemplate/tests/test_bwc.py
zope/app/pagetemplate/tests/test_engine.py
zope/app/pagetemplate/tests/test_namedtemplate.py
zope/app/pagetemplate/tests/test_nested.py
zope/app/pagetemplate/tests/test_talesapi.py
zope/app/pagetemplate/tests/test_urlquote.py
zope/app/pagetemplate/tests/testusage.pt
zope/app/pagetemplate/tests/testpackage/__init__.py
zope/app/pagetemplate/tests/testpackage/content.py
zope/app/pagetemplate/tests/testpackage/default.pt
zope/app/pagetemplate/tests/testpackage/nothing.pt
zope/app/pagetemplate/tests/testpackage/view.pt
zope_app_pagetemplate-6.0.dist-info/licenses/LICENSE.txt
zope_app_pagetemplate-6.0.dist-info/METADATA
zope_app_pagetemplate-6.0.dist-info/WHEEL
zope_app_pagetemplate-6.0.dist-info/top_level.txt
zope_app_pagetemplate-6.0.dist-info/RECORD
