Metadata-Version: 2.4
Name: zope.app.pagetemplate
Version: 6.0
Summary: PageTemplate integration for Zope 3
Home-page: https://github.com/zopefoundation/zope.app.pagetemplate
Author: Zope Foundation and Contributors
Author-email: zope-dev@zope.dev
License: ZPL-2.1
Classifier: Development Status :: 5 - Production/Stable
Classifier: Environment :: Web Environment
Classifier: Intended Audience :: Developers
Classifier: License :: OSI Approved :: Zope Public License
Classifier: Programming Language :: Python
Classifier: Programming Language :: Python :: 3.9
Classifier: Programming Language :: Python :: 3.10
Classifier: Programming Language :: Python :: 3.11
Classifier: Programming Language :: Python :: 3.12
Classifier: Programming Language :: Python :: 3.13
Classifier: Programming Language :: Python :: Implementation :: CPython
Classifier: Programming Language :: Python :: Implementation :: PyPy
Classifier: Natural Language :: English
Classifier: Operating System :: OS Independent
Classifier: Topic :: Internet :: WWW/HTTP
Classifier: Framework :: Zope :: 3
Requires-Python: >=3.9
License-File: LICENSE.txt
Requires-Dist: setuptools
Requires-Dist: zope.browserpage>=3.12.0
Requires-Dist: zope.component[hook]
Requires-Dist: zope.configuration
Requires-Dist: zope.dublincore
Requires-Dist: zope.i18nmessageid
Requires-Dist: zope.interface
Requires-Dist: zope.pagetemplate>=3.5.1
Requires-Dist: zope.schema
Requires-Dist: zope.security
Requires-Dist: zope.size
Requires-Dist: zope.tales
Requires-Dist: zope.traversing
Provides-Extra: test
Requires-Dist: zope.component[hook,test]; extra == "test"
Requires-Dist: zope.container; extra == "test"
Requires-Dist: zope.publisher; extra == "test"
Requires-Dist: zope.testrunner>=6.4; extra == "test"
Dynamic: author
Dynamic: author-email
Dynamic: classifier
Dynamic: description
Dynamic: home-page
Dynamic: license
Dynamic: license-file
Dynamic: provides-extra
Dynamic: requires-dist
Dynamic: requires-python
Dynamic: summary
